synthesizable_verilog/synthesizable_rca_8bit_adder.v
module eight_bit_adder (
 a,
 b,
 cin,
 cout,
 sum,
 clk,
 rst
);
input [7:0]a,b;
input cin,clk,rst;
output  reg cout;
output  reg [7:0]sum;
reg [6:0]bit_carry;
always@(posedge clk or negedge rst) begin
    if (~rst) begin
    cout<=0;
    sum<=0;
    end
    else begin
    {bit_carry[0],sum[0]}<=a[0]+b[0]+cin;
    {bit_carry[1],sum[1]}<=a[1]+b[1]+bit_carry[0];
    {bit_carry[2],sum[2]}<=a[2]+b[2]+bit_carry[1];
    {bit_carry[3],sum[3]}<=a[3]+b[3]+bit_carry[2];
    {bit_carry[4],sum[4]}<=a[4]+b[4]+bit_carry[3];
    {bit_carry[5],sum[5]}<=a[5]+b[5]+bit_carry[4];
    {bit_carry[6],sum[6]}<=a[6]+b[6]+bit_carry[5];
    {cout,sum[7]}<=a[7]+b[7]+bit_carry[6];
    end
end
endmodule //8_bit_adder

tb_rca_adder.v
module tb_rca_bitadder ();

reg [7:0] a,b;
output [7:0] sum;
output  cout;
reg rst,clk;
reg cin;
parameter delay=140; 
eight_bit_adder m1(a,b,cin,cout,sum,clk,rst);

initial begin
   $dumpfile("dump.vcd"); 
   $dumpvars;
end

initial begin
  clk=0;
     forever #10 clk = ~clk;  
end 
initial begin                                                  
#10a=32;b=32;cin=1'b0; rst=1;                
// #delay a=1;b=1;
// #delay a=20;b=20;cin=0;
// #delay a=75;b=75;cin=0;
// #delay a=128;b=128;cin=0;
// #delay a=200;b=200;cin=0;                                                                                 
end 
// initial begin
//   clk=0;
//      forever #10 clk = ~clk;  
// end 


initial begin 
    #1000 $finish;
end


endmodule

dump.vcd
$date
	Mon Jan 23 19:43:10 2023
$end
$version
	Icarus Verilog
$end
$timescale
	1s
$end
$scope module tb_rca_bitadder $end
$var wire 8 ! sum [7:0] $end
$var wire 1 " cout $end
$var reg 8 # a [7:0] $end
$var reg 8 $ b [7:0] $end
$var reg 1 % cin $end
$var reg 1 & clk $end
$var reg 1 ' rst $end
$scope module m1 $end
$var wire 8 ( a [7:0] $end
$var wire 8 ) b [7:0] $end
$var wire 1 % cin $end
$var wire 1 & clk $end
$var wire 1 ' rst $end
$var reg 7 * bit_carry [6:0] $end
$var reg 1 " cout $end
$var reg 8 + sum [7:0] $end
$upscope $end
$upscope $end
$enddefinitions $end
#0
$dumpvars
bx +
bx *
bx )
bx (
x'
0&
x%
bx $
bx #
x"
bx !
$end
#10
bx0 *
bx0 !
bx0 +
1'
0%
b100000 $
b100000 )
b100000 #
b100000 (
1&
#20
0&
#30
bx00 *
bx00 !
bx00 +
1&
#40
0&
#50
bx000 *
bx000 !
bx000 +
1&
#60
0&
#70
bx0000 *
bx0000 !
bx0000 +
1&
#80
0&
#90
bx00000 *
bx00000 !
bx00000 +
1&
#100
0&
#110
bx100000 *
bx000000 !
bx000000 +
1&
#120
0&
#130
b100000 *
bx1000000 !
bx1000000 +
1&
#140
0&
#150
0"
b1000000 !
b1000000 +
1&
