8_bit_adder.v
module eight_bit_adder (
 a,
 b,
 cin,
 cout,
 sum,
 clk,
 rst
);
input [7:0]a,b;
input cin,clk,rst;
output   cout;
output   [7:0]sum;
wire [6:0]bit_carry;

wire [7:0] a_d,b_d,a_d_bar,b_d_bar;

dff_8 d0(
    a_d,a_d_bar,a,clk,rst
);
dff_8 d1(
    b_d,b_d_bar,b,clk,rst
);

ADD_full u0(bit_carry[0],sum[0],a_d[0],b_d[0],cin);
ADD_full u1(bit_carry[1],sum[1],a_d[1],b_d[1],bit_carry[0]);
ADD_full u2(bit_carry[2],sum[2],a_d[2],b_d[2],bit_carry[1]);
ADD_full u3(bit_carry[3],sum[3],a_d[3],b_d[3],bit_carry[2]);
ADD_full u4(bit_carry[4],sum[4],a_d[4],b_d[4],bit_carry[3]);
ADD_full u5(bit_carry[5],sum[5],a_d[5],b_d[5],bit_carry[4]);
ADD_full u6(bit_carry[6],sum[6],a_d[6],b_d[6],bit_carry[5]);
ADD_full u7(cout,sum[7],a_d[7],b_d[7],bit_carry[6]);

// always@(posedge clk or negedge rst) begin
//     if (~rst) begin
//     cout<=0;
//     sum<=0;
//     end
//     else begin
//     {bit_carry[0],sum[0]}<=a[0]+b[0]+cin;
//     {bit_carry[1],sum[1]}<=a[1]+b[1]+bit_carry[0];
//     {bit_carry[2],sum[2]}<=a[2]+b[2]+bit_carry[1];
//     {bit_carry[3],sum[3]}<=a[3]+b[3]+bit_carry[2];
//     {bit_carry[4],sum[4]}<=a[4]+b[4]+bit_carry[3];
//     {bit_carry[5],sum[5]}<=a[5]+b[5]+bit_carry[4];
//     {bit_carry[6],sum[6]}<=a[6]+b[6]+bit_carry[5];
//     {cout,sum[7]}<=a[7]+b[7]+bit_carry[6];
//     end
// end
endmodule //8_bit_adder

module ADD_half_nogate(output cout,sum, input a,b);


assign      sum=a^b;
assign     cout=a&&b;


endmodule

module ADD_full(output c_out,sum, input a,b,cin);
wire w1, w2, w3;

ADD_half_nogate M1(w2,w1,a,b);
ADD_half_nogate M2(w3,sum,cin,w1);

assign c_out=w3||w2;
    
endmodule

module dff_8 (
    q_e,q_e_bar,data,clk,rst
);
output reg [7:0] q_e;
output [7:0] q_e_bar;

input [7:0] data;
input clk,rst;

assign q_e_bar=~q_e;
always @(posedge clk or negedge rst )begin
     if (~rst) begin
     q_e<=0;   
    end
    else begin
      q_e<=data;  
    end
end


endmodule //8_bit_dff

tb_8_dff.v

module tb_8_dff (
    
);

wire [7:0] q_e;
wire [7:0] q_e_bar;

reg [7:0] data;
reg clk,rst;

dff_8 u1(
    q_e,q_e_bar,data,clk,rst
);

initial begin
  clk=0;
     forever #10 clk = ~clk;  
end 
 initial begin
   $dumpfile("dump.vcd"); 
   $dumpvars;
 end
initial begin 
    #1000 $finish;
end
initial begin
    #100 data=0;rst=1;
    #100 data=23;
    #100 data=2;
    #100 data=11;
    #100 data=50;
    #100 data=60;
    #100 data=112;
    #100 data=1;
end




endmodule //tb_8_dff

dump.vcd
$date
	Mon Jan 23 23:09:45 2023
$end
$version
	Icarus Verilog
$end
$timescale
	1s
$end
$scope module tb_8_dff $end
$var wire 8 ! q_e_bar [7:0] $end
$var wire 8 " q_e [7:0] $end
$var reg 1 # clk $end
$var reg 8 $ data [7:0] $end
$var reg 1 % rst $end
$scope module u1 $end
$var wire 1 # clk $end
$var wire 8 & data [7:0] $end
$var wire 8 ' q_e_bar [7:0] $end
$var wire 1 % rst $end
$var reg 8 ( q_e [7:0] $end
$upscope $end
$upscope $end
$enddefinitions $end
#0
$dumpvars
bx (
bx '
bx &
x%
bx $
0#
bx "
bx !
$end
#10
1#
#20
0#
#30
1#
#40
0#
#50
1#
#60
0#
#70
1#
#80
0#
#90
1#
#100
0#
1%
b0 $
b0 &
#110
b11111111 !
b11111111 '
b0 "
b0 (
1#
#120
0#
#130
1#
#140
0#
#150
1#
#160
0#
#170
1#
#180
0#
#190
1#
#200
0#
b10111 $
b10111 &
#210
b11101000 !
b11101000 '
b10111 "
b10111 (
1#
#220
0#
#230
1#
#240
0#
#250
1#
#260
0#
#270
1#
#280
0#
#290
1#
#300
0#
b10 $
b10 &
#310
b11111101 !
b11111101 '
b10 "
b10 (
1#
#320
0#
#330
1#
#340
0#
#350
1#
#360
0#
#370
1#
#380
0#
#390
1#
#400
0#
b1011 $
b1011 &
#410
b11110100 !
b11110100 '
b1011 "
b1011 (
1#
#420
0#
#430
1#
#440
0#
#450
1#
#460
0#
#470
1#
#480
0#
#490
1#
#500
0#
b110010 $
b110010 &
#510
b11001101 !
b11001101 '
b110010 "
b110010 (
1#
#520
0#
#530
1#
#540
0#
#550
1#
#560
0#
#570
1#
#580
0#
#590
1#
#600
0#
b111100 $
b111100 &
#610
b11000011 !
b11000011 '
b111100 "
b111100 (
1#
#620
0#
#630
1#
#640
0#
#650
1#
#660
0#
#670
1#
#680
0#
#690
1#
#700
0#
b1110000 $
b1110000 &
#710
b10001111 !
b10001111 '
b1110000 "
b1110000 (
1#
#720
0#
#730
1#
#740
0#
#750
1#
#760
0#
#770
1#
#780
0#
#790
1#
#800
0#
b1 $
b1 &
#810
b11111110 !
b11111110 '
b1 "
b1 (
1#
