4_bit_shifter.v
module four_bit_shifter(A,E,clk,rst);

output  reg A;
reg B,C,D;
input clk,rst,E;

always @ (posedge clk or posedge rst) begin
  if(rst)begin
    A<=0;
    B<=0;
    C<=0;
    D<=0;
  end
  else begin
    A<=B;
    B<=C;
    C<=D;
    D<=E;
  end
end

endmodule

basic_circuits/tb_shifter.v
module t_shifter();
wire A;
reg E,clk,rst;
four_bit_shifter M1(A,E,clk,rst);
 initial begin
   $dumpfile("dump.vcd"); 
   $dumpvars;
 end
initial begin
  clk=0;
     forever #10 clk = ~clk;  
end 
initial begin 
    #200 $finish;
end
initial begin
    #10 E=0;rst=0;
    #10 E=1;
    #10 E=1;
    #10 E=0;rst=0;
    #10 E=0;rst=0;
    #10 E=1;
    #10 E=1;
    #10 E=1;
    #10 E=0;
    #10 E=0;
    #10 E=0;
    #10 E=0;
    #10 E=1;
    #10 E=1;
    #10 E=0;
    #10 E=1;
    #10 E=0;rst=1;
    #10 E=0;rst=0;


end
endmodule

dump.vcd
$date
	Sun Jan 22 17:51:42 2023
$end
$version
	Icarus Verilog
$end
$timescale
	1s
$end
$scope module t_shifter $end
$var wire 1 ! A $end
$var reg 1 " E $end
$var reg 1 # clk $end
$var reg 1 $ rst $end
$scope module M1 $end
$var wire 1 " E $end
$var wire 1 # clk $end
$var wire 1 $ rst $end
$var reg 1 ! A $end
$var reg 1 % B $end
$var reg 1 & C $end
$var reg 1 ' D $end
$upscope $end
$upscope $end
$enddefinitions $end
#0
$dumpvars
x'
x&
x%
x$
0#
x"
x!
$end
#10
0'
0$
0"
1#
#20
1"
0#
#30
1'
0&
1#
#40
0"
0#
#50
0'
1&
0%
1#
#60
1"
0#
#70
1'
0&
1%
0!
1#
#80
0#
#90
0'
1&
0%
1!
0"
1#
#100
0#
#110
0&
1%
0!
1#
#120
0#
#130
1'
0%
1!
1"
1#
#140
0#
#150
0'
1&
0!
0"
1#
#160
1"
0#
#170
0&
1$
0"
1#
#180
0$
0#
