FSM/drink.v
// input coin :2 and 1  sell drink when input coin is 4 enough and give change automatically

module drink_FSM (
    coin,
    change,
    drink,
    clk,
    rst
);
input  clk,rst; 
input [1:0] coin;// 0 means 0 ,  1 means 1, 2 means 2.
output reg [1:0] change ; //0 means 0, 1 means 1, 2 means 2;
output reg drink;
parameter            init   = 3'd0 ;
parameter            GET_1  = 3'd1 ;
parameter            GET_2  = 3'd2 ;
parameter            GET_3  = 3'd3 ;

reg [2:0]current_state;
reg [2:0]next_state;

always @(posedge clk or negedge rst) begin
    if (~rst)begin
        current_state<=init;
    end
    else begin
        current_state<=next_state;
    end
end

always @(*) begin
   case (current_state)

      init : case (coin)
              1:next_state<= GET_1;
              2:next_state<= GET_2;
       default: next_state<= current_state; 
             endcase 
      GET_1 : case (coin)
              1:next_state<= GET_2;
              2:next_state<= GET_3;
       default: next_state<= current_state; 
              endcase 
      GET_2 : case (coin)
              1:next_state<= GET_3;
              2:next_state<= init;
       default: next_state<= current_state; 
              endcase 
      GET_3 : case (coin)
              1:next_state<= init;
              2:next_state<= init;
       default: next_state<= current_state; 
              endcase 
             
    default: next_state<=init;
   endcase
end
always @(posedge clk or negedge rst) begin
    change <=0;
    drink  <=0;
    if (~rst)begin
        change <=0;
        drink  <=0;
    end
    else if (current_state==GET_3&&coin==1) begin
        drink  <=1;
    end
    else if (current_state==GET_3&&coin==2)begin
        drink  <=1;
        change <=1;
    end
    else if (current_state==GET_2&&coin==2)begin
        drink  <=1;
    end
end


endmodule //drink

FSM/tb_drink.v
module tb_drink (
    
);

reg  clk,rst; 
reg [1:0] coin;// 0 means 0 ,  1 means 1, 2 means 2.
wire [1:0] change ; //0 means 0, 1 means 1, 2 means 2;
wire drink;

drink_FSM drink_seller (coin,  change, drink,clk, rst);

initial begin
    clk=0;
    forever #10 clk = ~clk;  
end 

initial begin
   $dumpfile("dump.vcd"); 
   $dumpvars;
 end
initial begin 
    #200 $finish;
end
initial begin
        rst =0;
    #10 rst =1;
    #10 coin =2;

end





endmodule //tb_drink

FSM/dump.vcd
$date
	Sun Jan 29 17:58:08 2023
$end
$version
	Icarus Verilog
$end
$timescale
	1s
$end
$scope module tb_drink $end
$var wire 1 ! drink $end
$var wire 2 " change [1:0] $end
$var reg 1 # clk $end
$var reg 2 $ coin [1:0] $end
$var reg 1 % rst $end
$scope module drink_seller $end
$var wire 1 # clk $end
$var wire 2 & coin [1:0] $end
$var wire 1 % rst $end
$var reg 2 ' change [1:0] $end
$var reg 3 ( current_state [2:0] $end
$var reg 1 ! drink $end
$var reg 3 ) next_state [2:0] $end
$upscope $end
$upscope $end
$enddefinitions $end
#0
$dumpvars
b0 )
b0 (
b0 '
bx &
0%
bx $
0#
b0 "
0!
$end
#10
1%
1#
#20
b10 )
b10 $
b10 &
0#
#30
b0 )
b10 (
1#
#40
0#
#50
b10 )
1!
b0 (
1#
#60
0#
#70
b0 )
b10 (
0!
1#
#80
0#
#90
b10 )
1!
b0 (
1#
#100
0#
#110
b0 )
b10 (
0!
1#
#120
0#
#130
b10 )
1!
b0 (
1#
#140
0#
#150
b0 )
b10 (
0!
1#
#160
0#
#170
b10 )
1!
b0 (
1#
#180
0#
#190
b0 )
b10 (
0!
1#
