basic_circuits/LCA_64.v
module LCA_64bit (
    a,b,cin,cout_r,sum_r,clk,rst
);
input [63:0]a,b;
input cin,clk,rst;

output reg [63:0]sum_r;
output reg cout_r;

wire [63:0] p;
wire [63:0] g;
wire [63:0] sum;
wire cout;
wire [63:0] c;

pg_gen u0 (a,b,p,g);

assign c[0]=cin;  //cin 0th bit
// assign c[1]=g[0]|(p[0]&c[0]); //cin 1st bit
// assign c[2]=g[1]|(p[1]&c[1]); //cin 2nd bit
// assign c[3]=g[2]|(p[2]&c[2]); //cin 3rd bit
// assign c[4]=g[3]|(p[3]&c[3]); // cin 4th bit
// assign c[5]=g[4]|(p[4]&c[4]); //cin 5th bit
// assign c[6]=g[5]|(p[5]&c[5]); //cin 6th bit
// assign c[7]=g[6]|(p[6]&c[6]);  //cin 7th bit

assign c[63:1]=g[62:0]|(p[62:0]&c[62:0]); // 62 bits

assign cout = g[63]|(p[63]&c[63]); //cin 63th bit
// assign cout=g[7]|(p[7]&c[7]); //cin 8th bit

// assign sum = p^c;
assign sum[0] = p[0]^c[0]; //sum 0th bit
assign sum[63:1] = p[63:1]^c[63:1]; //63 bits
// assign sum[1] = p[1]^c[1]; //sum 1st bit
// assign sum[2] = p[2]^c[2]; //sum 2nd bit
// assign sum[3] = p[3]^c[3]; //sum 3rd bit
// assign sum[4] = p[4]^c[4]; //sum 4th bit
// assign sum[5] = p[5]^c[5]; //sum 5th bit
// assign sum[6] = p[6]^c[6]; //sum 6th bit
// assign sum[7] = p[7]^c[7]; //sum 7th bit
always @(posedge clk or negedge rst) begin
   if (~rst) begin
        sum_r  <=0;
        cout_r <=0;
   end
   else begin
        sum_r  <=sum;
        cout_r <=cout;
   end
         
end
endmodule //LCA_8bit

module pg_gen (
    a,b,p,g    
);
input [63:0]a,b;
output [63:0]p,g;

assign p=a^b;
assign g=a&b;

endmodule //LCA_8bit

basic_circuits/tb_lca64.v
module tb_lca_bitadder ();

reg [63:0] a,b;
output [63:0] sum;
output  cout;
reg rst,clk;
reg cin;
parameter delay=20; 
LCA_64bit  lca (a,b,cin,cout,sum,clk,rst
);
initial begin
   $dumpfile("dump.vcd"); 
   $dumpvars;
end

initial begin
  clk=0;
     forever #10 clk = ~clk;  
end 
initial begin                                                  
#10   a=2;b=5;cin=1'b0;             
#delay a=1;b=1;
#delay a=20;b=20;cin=1;
#delay a=75;b=75;cin=1;
#delay a=128;b=128;cin=0;
#delay a=200;b=20;cin=0;                                                                                 
end 
// initial begin
//   clk=0;
//      forever #10 clk = ~clk;  
// end 


initial begin 
    #1000 $finish;
end


endmodule

basic_circuits/dump.vcd
$date
	Fri Feb 24 23:30:08 2023
$end
$version
	Icarus Verilog
$end
$timescale
	1s
$end
$scope module tb_lca_bitadder $end
$var wire 64 ! sum [63:0] $end
$var wire 1 " cout $end
$var reg 64 # a [63:0] $end
$var reg 64 $ b [63:0] $end
$var reg 1 % cin $end
$var reg 1 & clk $end
$var reg 1 ' rst $end
$scope module lca $end
$var wire 64 ( a [63:0] $end
$var wire 64 ) b [63:0] $end
$var wire 1 % cin $end
$var wire 1 & clk $end
$var wire 1 * cout $end
$var wire 1 ' rst $end
$var wire 64 + sum [63:0] $end
$var wire 64 , p [63:0] $end
$var wire 64 - g [63:0] $end
$var wire 64 . c [63:0] $end
$var reg 1 " cout_r $end
$var reg 64 / sum_r [63:0] $end
$scope module u0 $end
$var wire 64 0 a [63:0] $end
$var wire 64 1 b [63:0] $end
$var wire 64 2 g [63:0] $end
$var wire 64 3 p [63:0] $end
$upscope $end
$upscope $end
$upscope $end
$enddefinitions $end
#0
$dumpvars
bx 3
bx 2
bx 1
bx 0
bx /
bx .
bx -
bx ,
bx +
x*
bx )
bx (
x'
0&
x%
bx $
bx #
x"
bx !
$end
#10
0*
b111 +
b111 ,
b111 3
b0 -
b0 2
b0 .
0%
b101 $
b101 )
b101 1
b10 #
b10 (
b10 0
1&
#20
0&
#30
0"
b111 !
b111 /
b10 +
b10 .
b0 ,
b0 3
b1 -
b1 2
1&
b1 $
b1 )
b1 1
b1 #
b1 (
b1 0
#40
0&
#50
b10 !
b10 /
b101001 +
b10100 -
b10100 2
1&
b101001 .
1%
b10100 $
b10100 )
b10100 1
b10100 #
b10100 (
b10100 0
#60
0&
#70
b101001 !
b101001 /
b10010111 +
b10010111 .
b1001011 -
b1001011 2
1&
b1001011 $
b1001011 )
b1001011 1
b1001011 #
b1001011 (
b1001011 0
#80
0&
#90
b10010111 !
b10010111 /
b100000000 +
b10000000 -
b10000000 2
1&
b100000000 .
0%
b10000000 $
b10000000 )
b10000000 1
b10000000 #
b10000000 (
b10000000 0
#100
0&
#110
b100000000 !
b100000000 /
b11011100 +
b0 .
b11011100 ,
b11011100 3
b0 -
b0 2
1&
b10100 $
b10100 )
b10100 1
b11001000 #
b11001000 (
b11001000 0
#120
0&
#130
b11011100 !
b11011100 /
1&
