basic_circuits/CSA_8bit.v
module CSA_8bit (
    a,b,cin_or_z,sum,cout,clk,rst
);
input [7:0] a,b;
output reg [7:0] sum;
input [7:0] cin_or_z;
input clk,rst;
output reg cout;

wire [7:0]c1,c2;

wire [7:0]s1,s2;

ADD_full add1(c1[0],s1[0],a[0],b[0],cin_or_z[0]);//first bit of sum and carry
ADD_full add2(c1[1],s1[1],a[1],b[1],cin_or_z[1]); // 2nd carry
ADD_full add3(c1[2],s1[2],a[2],b[2],cin_or_z[2]);  // 3rd carry
ADD_full add4(c1[3],s1[3],a[3],b[3],cin_or_z[3]);  // 4th carry
ADD_full add5(c1[4],s1[4],a[4],b[4],cin_or_z[4]);  // 5th carry
ADD_full add6(c1[5],s1[5],a[5],b[5],cin_or_z[5]);  // 6th carry
ADD_full add7(c1[6],s1[6],a[6],b[6],cin_or_z[6]);  // 7th carry
ADD_full add8(c1[7],s1[7],a[7],b[7],cin_or_z[7]);  // 8th carry

ADD_full add9(c2[0],s2[1],s1[1],c1[0],1'b0); // 2nd sum
ADD_full add10(c2[1],s2[2],s1[2],c1[1],c2[0]); // 3rd sum
ADD_full add11(c2[2],s2[3],s1[3],c1[2],c2[1]); // 4th sum
ADD_full add12(c2[3],s2[4],s1[4],c1[3],c2[2]); // 5th sum
ADD_full add13(c2[4],s2[5],s1[5],c1[4],c2[3]); // 6th sum
ADD_full add14(c2[5],s2[6],s1[6],c1[5],c2[4]); // 7th sum
ADD_full add15(c2[6],s2[7],s1[7],c1[6],c2[5]); // 8th sum

assign s2[0]=s1[0];
always @(posedge clk or negedge rst) begin
    if (~rst) begin
        sum<=8'b0;
        cout<=1'b0;
    end
    else begin
        sum<=s2;
        cout<=c2[6];
end
end
endmodule //CSA_8bit





module ADD_full(output c_out,sum, input a,b,cin);
// wire w1, w2, w3;

assign sum=a^b^cin;

assign c_out=(a&b)|(cin&(a^b));
    
endmodule

basic_circuits/tb_csa_8bit.v
module tb_csa_bitadder ();

reg [7:0] a,b;
output [7:0] sum;
output  cout;
reg rst,clk;
reg cin;
parameter delay=20; 
CSA_8bit  csa(
    a,b,cin,sum,cout,clk,rst
);
initial begin
   $dumpfile("dump.vcd"); 
   $dumpvars;
end

initial begin
  clk=0;
     forever #10 clk = ~clk;  
end 
initial begin                                                  
#10   a=2;b=5;cin=1'b0;             
#delay a=1;b=1;
#delay a=20;b=20;cin=1;
#delay a=75;b=75;cin=1;
#delay a=128;b=128;cin=0;
#delay a=200;b=20;cin=0;                                                                                 
end 
// initial begin
//   clk=0;
//      forever #10 clk = ~clk;  
// end 


initial begin 
    #1000 $finish;
end


endmodule

basic_circuits/dump.vcd
$date
	Sat Feb 25 20:30:28 2023
$end
$version
	Icarus Verilog
$end
$timescale
	1s
$end
$scope module tb_csa_bitadder $end
$var wire 8 ! sum [7:0] $end
$var wire 1 " cout $end
$var reg 8 # a [7:0] $end
$var reg 8 $ b [7:0] $end
$var reg 1 % cin $end
$var reg 1 & clk $end
$var reg 1 ' rst $end
$scope module csa $end
$var wire 8 ( a [7:0] $end
$var wire 8 ) b [7:0] $end
$var wire 8 * cin_or_z [7:0] $end
$var wire 1 & clk $end
$var wire 1 ' rst $end
$var wire 8 + s2 [7:0] $end
$var wire 8 , s1 [7:0] $end
$var wire 8 - c2 [7:0] $end
$var wire 8 . c1 [7:0] $end
$var reg 1 " cout $end
$var reg 8 / sum [7:0] $end
$scope module add1 $end
$var wire 1 0 a $end
$var wire 1 1 b $end
$var wire 1 2 c_out $end
$var wire 1 3 cin $end
$var wire 1 4 sum $end
$upscope $end
$scope module add10 $end
$var wire 1 5 a $end
$var wire 1 6 b $end
$var wire 1 7 c_out $end
$var wire 1 8 cin $end
$var wire 1 9 sum $end
$upscope $end
$scope module add11 $end
$var wire 1 : a $end
$var wire 1 ; b $end
$var wire 1 < c_out $end
$var wire 1 = cin $end
$var wire 1 > sum $end
$upscope $end
$scope module add12 $end
$var wire 1 ? a $end
$var wire 1 @ b $end
$var wire 1 A c_out $end
$var wire 1 B cin $end
$var wire 1 C sum $end
$upscope $end
$scope module add13 $end
$var wire 1 D a $end
$var wire 1 E b $end
$var wire 1 F c_out $end
$var wire 1 G cin $end
$var wire 1 H sum $end
$upscope $end
$scope module add14 $end
$var wire 1 I a $end
$var wire 1 J b $end
$var wire 1 K c_out $end
$var wire 1 L cin $end
$var wire 1 M sum $end
$upscope $end
$scope module add15 $end
$var wire 1 N a $end
$var wire 1 O b $end
$var wire 1 P c_out $end
$var wire 1 Q cin $end
$var wire 1 R sum $end
$upscope $end
$scope module add2 $end
$var wire 1 S a $end
$var wire 1 T b $end
$var wire 1 U c_out $end
$var wire 1 V cin $end
$var wire 1 W sum $end
$upscope $end
$scope module add3 $end
$var wire 1 X a $end
$var wire 1 Y b $end
$var wire 1 Z c_out $end
$var wire 1 [ cin $end
$var wire 1 \ sum $end
$upscope $end
$scope module add4 $end
$var wire 1 ] a $end
$var wire 1 ^ b $end
$var wire 1 _ c_out $end
$var wire 1 ` cin $end
$var wire 1 a sum $end
$upscope $end
$scope module add5 $end
$var wire 1 b a $end
$var wire 1 c b $end
$var wire 1 d c_out $end
$var wire 1 e cin $end
$var wire 1 f sum $end
$upscope $end
$scope module add6 $end
$var wire 1 g a $end
$var wire 1 h b $end
$var wire 1 i c_out $end
$var wire 1 j cin $end
$var wire 1 k sum $end
$upscope $end
$scope module add7 $end
$var wire 1 l a $end
$var wire 1 m b $end
$var wire 1 n c_out $end
$var wire 1 o cin $end
$var wire 1 p sum $end
$upscope $end
$scope module add8 $end
$var wire 1 q a $end
$var wire 1 r b $end
$var wire 1 s c_out $end
$var wire 1 t cin $end
$var wire 1 u sum $end
$upscope $end
$scope module add9 $end
$var wire 1 v a $end
$var wire 1 w b $end
$var wire 1 x c_out $end
$var wire 1 y cin $end
$var wire 1 z sum $end
$upscope $end
$upscope $end
$upscope $end
$enddefinitions $end
#0
$dumpvars
xz
0y
xx
xw
xv
xu
0t
xs
xr
xq
xp
0o
xn
xm
xl
xk
0j
xi
xh
xg
xf
0e
xd
xc
xb
xa
0`
x_
x^
x]
x\
0[
xZ
xY
xX
xW
0V
xU
xT
xS
xR
xQ
xP
xO
xN
xM
xL
xK
xJ
xI
xH
xG
xF
xE
xD
xC
xB
xA
x@
x?
x>
x=
x<
x;
x:
x9
x8
x7
x6
x5
x4
x3
x2
x1
x0
bx /
bx .
bzxxxxxxx -
bx ,
bx +
b0x *
bx )
bx (
x'
0&
x%
bx $
bx #
x"
bx !
$end
#10
0>
0=
07
19
0C
0H
0M
0R
08
0B
0G
0L
0Q
1z
0x
0<
0A
0F
0K
bz0000000 -
0P
0w
1v
06
15
0;
0:
0@
0?
0E
0D
0J
0I
0O
0N
b111 +
02
1W
0U
1\
0Z
0a
0_
0f
0d
0k
0i
0p
0n
0u
b0 .
0s
b111 ,
14
03
11
0T
1Y
0^
0c
0h
0m
0r
00
1S
0X
0]
0b
0g
0l
0q
b0 *
0%
b101 $
b101 )
b10 #
b10 (
1&
#20
0&
#30
0"
b111 !
b111 /
09
05
b10 +
1w
0v
0\
04
b1 .
12
b0 ,
0W
0Y
10
0S
1&
b1 $
b1 )
b1 #
b1 (
#40
0&
#50
b10 !
b10 /
0z
1>
1H
0w
1;
1E
b101001 +
02
1Z
b10100 .
1d
b1 ,
14
13
01
1Y
1c
00
1X
1b
1&
b1 *
1%
b10100 $
b10100 )
b10100 #
b10100 (
#60
0&
#70
b101001 !
b101001 /
1z
19
0>
1C
0H
b10010111 +
1R
1w
16
0;
1@
0E
1O
12
1U
0Z
1_
0d
b1001011 .
1n
11
1T
0Y
1^
0c
1m
10
1S
0X
1]
0b
1l
1&
b1001011 $
b1001011 )
b1001011 #
b1001011 (
#80
0&
#90
b10010111 !
b10010111 /
0z
09
0C
0R
0w
06
0@
0O
b0 +
02
0U
0_
0n
b10000000 .
1s
b0 ,
04
03
01
0T
0^
0m
1r
00
0S
0]
0l
1q
1&
b0 *
0%
b10000000 $
b10000000 )
b10000000 #
b10000000 (
#100
0&
#110
b0 !
b0 /
19
1C
1R
1>
b11011100 +
1M
15
1?
1N
1:
1I
1\
1f
1u
b0 .
0s
1a
b11011100 ,
1p
1Y
1c
0r
1]
1l
1&
b10100 $
b10100 )
b11001000 #
b11001000 (
#120
0&
#130
b11011100 !
b11011100 /
1&
